intelligames/__init__.py
intelligames-0.0.1.dist-info/LICENSE
intelligames-0.0.1.dist-info/METADATA
intelligames-0.0.1.dist-info/WHEEL
intelligames-0.0.1.dist-info/top_level.txt
intelligames-0.0.1.dist-info/RECORD
